pycatia/__init__.py
pycatia/cat_logger.py
pycatia/version.py
pycatia/abq_automation_interfaces/__init__.py
pycatia/abq_automation_interfaces/abq_analysis_case.py
pycatia/abq_automation_interfaces/abq_analysis_cases.py
pycatia/abq_automation_interfaces/abq_analysis_model.py
pycatia/abq_automation_interfaces/abq_analytical_rigid_surface.py
pycatia/abq_automation_interfaces/abq_boundary_condition.py
pycatia/abq_automation_interfaces/abq_boundary_conditions.py
pycatia/abq_automation_interfaces/abq_clamp_bc.py
pycatia/abq_automation_interfaces/abq_concentrated_force.py
pycatia/abq_automation_interfaces/abq_damper_connection_property.py
pycatia/abq_automation_interfaces/abq_data_output_request.py
pycatia/abq_automation_interfaces/abq_data_output_requests.py
pycatia/abq_automation_interfaces/abq_displacement_bc.py
pycatia/abq_automation_interfaces/abq_display_group.py
pycatia/abq_automation_interfaces/abq_display_groups.py
pycatia/abq_automation_interfaces/abq_explicit_dynamics_step.py
pycatia/abq_automation_interfaces/abq_fastened_connection_enhancement.py
pycatia/abq_automation_interfaces/abq_fastened_pair.py
pycatia/abq_automation_interfaces/abq_field_output_request.py
pycatia/abq_automation_interfaces/abq_field_output_requests.py
pycatia/abq_automation_interfaces/abq_fields.py
pycatia/abq_automation_interfaces/abq_film_condition.py
pycatia/abq_automation_interfaces/abq_frequency_step.py
pycatia/abq_automation_interfaces/abq_gasket_property.py
pycatia/abq_automation_interfaces/abq_general_static_step.py
pycatia/abq_automation_interfaces/abq_global_element_assignment.py
pycatia/abq_automation_interfaces/abq_gravity.py
pycatia/abq_automation_interfaces/abq_heat_transfer_step.py
pycatia/abq_automation_interfaces/abq_history_output_request.py
pycatia/abq_automation_interfaces/abq_history_output_requests.py
pycatia/abq_automation_interfaces/abq_image_query.py
pycatia/abq_automation_interfaces/abq_initial_step.py
pycatia/abq_automation_interfaces/abq_initial_temperature.py
pycatia-0.9.3.dist-info/LICENSE.txt
pycatia-0.9.3.dist-info/METADATA
pycatia-0.9.3.dist-info/PKG-INFO [conflicted]
pycatia-0.9.3.dist-info/WHEEL
pycatia-0.9.3.dist-info/top_level.txt
pycatia-0.9.3.dist-info/RECORD
