Metadata-Version: 2.1
Name: pycatia
Version: 0.9.3
Summary: A python module to interface with the CATIA V5 COM object.
Home-page: https://github.com/evereux/pycatia
Author: Paul Bourne
Author-email: evereux@gmail.com
Classifier: Programming Language :: Python :: 3.9
Classifier: Programming Language :: Python :: 3.10
Classifier: License :: OSI Approved :: MIT License
Classifier: Operating System :: Microsoft :: Windows
Requires-Python: >=3.9
License-File: LICENSE.txt
Requires-Dist: pywin32>=224
